SimpleITK/utilities/Logger.py
SimpleITK/utilities/__init__.py
SimpleITK/utilities/_version.py
SimpleITK/utilities/dask.py
SimpleITK/utilities/fft.py
SimpleITK/utilities/make_isotropic.py
SimpleITK/utilities/overlay_bounding_boxes.py
SimpleITK/utilities/pyside.py
SimpleITK/utilities/resize.py
SimpleITK/utilities/slice_by_slice.py
SimpleITK/utilities/vtk.py
SimpleITKUtilities-0.3.0.dist-info/LICENSE
SimpleITKUtilities-0.3.0.dist-info/METADATA
SimpleITKUtilities-0.3.0.dist-info/NOTICE
SimpleITKUtilities-0.3.0.dist-info/WHEEL
SimpleITKUtilities-0.3.0.dist-info/top_level.txt
SimpleITKUtilities-0.3.0.dist-info/RECORD
