Metadata-Version: 2.1
Name: SimpleITKUtilities
Version: 0.3.0
Summary: A collection of utilities and integration tools to enhance SimpleITK.
Author-email: Bradley Lowekamp <blowekamp@mail.nih.gov>, Ziv Yaniv <zivyaniv@nih.gov>
Classifier: Programming Language :: Python :: 3
Classifier: License :: OSI Approved :: Apache Software License
Classifier: Operating System :: OS Independent
Requires-Python: >=3.8
License-File: LICENSE
License-File: NOTICE
Requires-Dist: SimpleITK >=2.3.0
Requires-Dist: numpy
Provides-Extra: dask
Requires-Dist: dask ; extra == 'dask'
Provides-Extra: pyside
Requires-Dist: PySide6 ; extra == 'pyside'
Provides-Extra: vtk
Requires-Dist: vtk >=9.0 ; extra == 'vtk'
